sainsmart/__init__.py
sainsmart/devices.py
sainsmart-0.3.1.dist-info/DESCRIPTION.rst
sainsmart-0.3.1.dist-info/METADATA
sainsmart-0.3.1.dist-info/RECORD
sainsmart-0.3.1.dist-info/WHEEL
sainsmart-0.3.1.dist-info/metadata.json
sainsmart-0.3.1.dist-info/top_level.txt
