Metadata-Version: 2.0
Name: sainsmart
Version: 0.3.1
Summary: sainsmart contains code for working with sainsmart products.
Home-page: https://github.com/vicyap/sainsmart
Author: Victor Yap
Author-email: victor@vicyap.com
License: MIT license
Keywords: sainsmart
Platform: UNKNOWN
Classifier: Development Status :: 4 - Beta
Classifier: Intended Audience :: Developers
Classifier: License :: OSI Approved :: MIT License
Classifier: Natural Language :: English
Classifier: Programming Language :: Python :: 2
Classifier: Programming Language :: Python :: 2.7
Classifier: Programming Language :: Python :: 3
Classifier: Programming Language :: Python :: 3.5
Classifier: Programming Language :: Python :: 3.6
Requires-Dist: requests (==2.18.0)
Requires-Dist: typing (==3.6.1)
